dytok/__init__.py
dytok/visionzip/__init__.py
dytok/visionzip/llava_arch.py
dytok/visionzip/main.py
dytok/visionzip/modeling_qwen2.py
dytok/visionzip/siglip_encoder.py
dytok/visionzip/utils.py
dytok-0.1.0.dist-info/licenses/LICENSE
dytok-0.1.0.dist-info/METADATA
dytok-0.1.0.dist-info/WHEEL
dytok-0.1.0.dist-info/top_level.txt
dytok-0.1.0.dist-info/RECORD
