Metadata-Version: 2.4
Name: dytok
Version: 0.1.0
Summary: A training-free compression paradigm that dynamically adjusts per-frame token retention ratios based on LLM's keyframe prior
Author-email: Yulin Li <yulin@stu.hit.edu.cn>
License:                                  Apache License
Project-URL: Homepage, https://dytok.github.io
Project-URL: Repository, https://github.com/yu-lin-li/DyToK
Project-URL: Bug Tracker, https://github.com/yu-lin-li/DyToK/issues
Classifier: Programming Language :: Python :: 3
Classifier: License :: OSI Approved :: Apache Software License
Requires-Python: >=3.9
License-File: LICENSE
Dynamic: license-file
